{
  "id": "17897861951602280",
  "text": "Up Up 🔥",
  "created_at": 1650376076,
  "did_report_as_spam": false,
  "owner": {
    "id": "619803582",
    "is_verified": false,
    "profile_pic_url": "https://instagram.fbsb8-2.fna.fbcdn.net/v/t51.2885-19/275741841_630010238073024_9198868928103208212_n.jpg?stp=dst-jpg_s150x150&_nc_ht=instagram.fbsb8-2.fna.fbcdn.net&_nc_cat=100&_nc_ohc=mU7dKkE5FzEAX9FAC0h&edm=AMrZAGUBAAAA&ccb=7-4&oh=00_AT95XzZd-HlSkknERnmXSRHJaRN1WqyQNmK5o7bb4vMgFA&oe=6268C40E&_nc_sid=9fb510",
    "username": "brunomorat0"
  },
  "likes": 1,
  "comments": 0
}